{
  "_class": "group",
  "do_objectID": "7A502504-4D71-49E3-9768-EC0317FAC665",
  "exportOptions": {
    "_class": "exportOptions",
    "do_objectID": "0CD7A21F-5DAF-450C-903B-71E8E99461D9",
    "exportFormats": [
    ],
    "includedLayerIds": [
    ],
    "layerOptions": 0,
    "shouldTrim": false
  },
  "frame": {
    "_class": "rect",
    "constrainProportions": false,
    "do_objectID": "CB0147B4-6351-4782-9F42-3D16917049FD",
    "height": 182,
    "width": 158,
    "x": 0,
    "y": 182
  },
  "hasClickThrough": false,
  "isFlippedHorizontal": false,
  "isFlippedVertical": false,
  "isLocked": false,
  "isVisible": true,
  "layerListExpandedType": 0,
  "layers": [
    {
      "class": "text",
      "id": "7B0A3156-E57C-478C-AC3B-41DB89C96422"
    },
    {
      "class": "shapeGroup",
      "id": "48EBDFC3-D7F3-4EDF-9167-788CEDD5BD2F"
    }
  ],
  "name": "3",
  "nameIsFixed": true,
  "resizingConstraint": 63,
  "resizingType": 0,
  "rotation": 0,
  "shouldBreakMaskChain": false,
  "style": {
    "_class": "style",
    "do_objectID": "2859051B-6478-4A95-9B7D-97BAA7F05497",
    "endDecorationType": 0,
    "miterLimit": 10,
    "startDecorationType": 0
  }
}