{
  "_class": "group",
  "do_objectID": "4DD32BF3-7C3C-4EE4-A965-711B876F6A01",
  "exportOptions": {
    "_class": "exportOptions",
    "do_objectID": "62066EB8-BF32-4EE5-B1E5-B577E99D1FF9",
    "exportFormats": [
    ],
    "includedLayerIds": [
    ],
    "layerOptions": 0,
    "shouldTrim": false
  },
  "frame": {
    "_class": "rect",
    "constrainProportions": false,
    "do_objectID": "A01D1CDC-26B1-40A7-AFFC-4BAEF217F8FD",
    "height": 30,
    "width": 66,
    "x": 98,
    "y": 0
  },
  "hasClickThrough": false,
  "isFlippedHorizontal": false,
  "isFlippedVertical": false,
  "isLocked": false,
  "isVisible": true,
  "layerListExpandedType": 0,
  "layers": [
    {
      "class": "shapeGroup",
      "id": "DB60ED0E-E130-4601-9B0A-E72AB7FC5EC4"
    },
    {
      "class": "group",
      "id": "D0C67577-B0F7-4E8E-A51C-F009D56842EC"
    },
    {
      "class": "text",
      "id": "26442231-F361-4DF0-962A-9AE541C819AE"
    }
  ],
  "name": "off switcher",
  "nameIsFixed": true,
  "resizingConstraint": 63,
  "resizingType": 0,
  "rotation": 0,
  "shouldBreakMaskChain": false,
  "style": {
    "_class": "style",
    "do_objectID": "0D4D9B8E-A7AA-4B1A-9F0C-964565325FE9",
    "endDecorationType": 0,
    "miterLimit": 10,
    "startDecorationType": 0
  }
}