{
  "_class": "shapeGroup",
  "clippingMaskMode": 0,
  "do_objectID": "8C009E4A-B47D-43DE-8822-4734CF17A1B7",
  "exportOptions": {
    "_class": "exportOptions",
    "do_objectID": "957718F9-2D70-4940-98CC-3FEE818AE640",
    "exportFormats": [
    ],
    "includedLayerIds": [
    ],
    "layerOptions": 0,
    "shouldTrim": false
  },
  "frame": {
    "_class": "rect",
    "constrainProportions": false,
    "do_objectID": "79B827D2-1528-4FFA-8CB0-794A1F8CA367",
    "height": 9.117276560464735,
    "width": 5.96716873449131,
    "x": 150.6498759305211,
    "y": 4.616195121951217
  },
  "hasClickThrough": false,
  "hasClippingMask": false,
  "isFlippedHorizontal": false,
  "isFlippedVertical": false,
  "isLocked": false,
  "isVisible": true,
  "layerListExpandedType": 0,
  "layers": [
    {
      "class": "shapePath",
      "id": "AB2ED8D1-7101-445B-89E1-FB79F541D6FE"
    }
  ],
  "name": "Fill 18",
  "nameIsFixed": false,
  "resizingConstraint": 63,
  "resizingType": 0,
  "rotation": 0,
  "shouldBreakMaskChain": false,
  "style": {
    "_class": "style",
    "blur": {
      "_class": "blur",
      "center": "{0.5, 0.5}",
      "do_objectID": "1BC80144-4686-40AB-B41E-CEA91C19AB77",
      "isEnabled": false,
      "motionAngle": 0,
      "radius": 3.902439024390244,
      "type": 0
    },
    "do_objectID": "95D08E7B-F00B-43CD-A257-7C637D3BB841",
    "endDecorationType": 0,
    "fills": [
      {
        "_class": "fill",
        "color": {
          "_class": "color",
          "alpha": 1,
          "blue": 1,
          "green": 1,
          "red": 1
        },
        "fillType": 0,
        "isEnabled": true,
        "noiseIndex": 0,
        "noiseIntensity": 0,
        "patternFillType": 1,
        "patternTileScale": 1
      }
    ],
    "miterLimit": 10,
    "startDecorationType": 0
  },
  "windingRule": 1
}