{
  "_class": "shapeGroup",
  "clippingMaskMode": 0,
  "do_objectID": "B36C8D11-A584-42F7-A149-96CC48F24399",
  "exportOptions": {
    "_class": "exportOptions",
    "do_objectID": "F96192EA-F598-4221-AB5F-E9A781F50021",
    "exportFormats": [
    ],
    "includedLayerIds": [
    ],
    "layerOptions": 0,
    "shouldTrim": false
  },
  "frame": {
    "_class": "rect",
    "constrainProportions": false,
    "do_objectID": "9E0C9BB0-4552-4A25-8BCB-720EEECF4A9E",
    "height": 288,
    "width": 304,
    "x": 21,
    "y": 0
  },
  "hasClickThrough": false,
  "hasClippingMask": false,
  "isFlippedHorizontal": false,
  "isFlippedVertical": false,
  "isLocked": false,
  "isVisible": true,
  "layerListExpandedType": 0,
  "layers": [
    {
      "class": "shapePath",
      "id": "F6DDFFBC-7CB7-4477-81E2-2CE9587EE98B"
    }
  ],
  "name": "Combined Shape",
  "nameIsFixed": false,
  "resizingConstraint": 63,
  "resizingType": 0,
  "rotation": 0,
  "shouldBreakMaskChain": false,
  "style": {
    "_class": "style",
    "blur": {
      "_class": "blur",
      "center": "{0.5, 0.5}",
      "do_objectID": "95B6048B-7516-4346-ADCB-BEA472627F15",
      "isEnabled": false,
      "motionAngle": 0,
      "radius": 4.198565673551466,
      "type": 0
    },
    "do_objectID": "EDE8536F-778D-4696-B432-B821BFF8B89E",
    "endDecorationType": 0,
    "fills": [
      {
        "_class": "fill",
        "color": {
          "_class": "color",
          "alpha": 1,
          "blue": 0.9764705882352941,
          "green": 0.9725490196078431,
          "red": 0.9529411764705882
        },
        "fillType": 0,
        "gradient": {
          "_class": "gradient",
          "elipseLength": 0,
          "from": "{0.5, 0}",
          "gradientType": 0,
          "stops": [
            {
              "_class": "gradientStop",
              "color": {
                "_class": "color",
                "alpha": 0.5,
                "blue": 1,
                "green": 1,
                "red": 1
              },
              "position": 0
            },
            {
              "_class": "gradientStop",
              "color": {
                "_class": "color",
                "alpha": 0.5,
                "blue": 0,
                "green": 0,
                "red": 0
              },
              "position": 1
            }
          ],
          "to": "{0.5, 1}"
        },
        "isEnabled": true,
        "noiseIndex": 0,
        "noiseIntensity": 0,
        "patternFillType": 1,
        "patternTileScale": 1
      }
    ],
    "miterLimit": 10,
    "startDecorationType": 0
  },
  "windingRule": 1
}