{
  "_class": "group",
  "do_objectID": "60402EA7-D21E-4B27-951E-5B46289AE70B",
  "exportOptions": {
    "_class": "exportOptions",
    "do_objectID": "CE894011-0B30-41BA-89D5-6F8EF4F5BBA3",
    "exportFormats": [
    ],
    "includedLayerIds": [
    ],
    "layerOptions": 0,
    "shouldTrim": false
  },
  "frame": {
    "_class": "rect",
    "constrainProportions": false,
    "do_objectID": "56EBA804-377B-48DC-9D9F-1AD7553588D2",
    "height": 134,
    "width": 420,
    "x": 0,
    "y": 196
  },
  "hasClickThrough": true,
  "isFlippedHorizontal": false,
  "isFlippedVertical": false,
  "isLocked": false,
  "isVisible": true,
  "layerListExpandedType": 1,
  "layers": [
    {
      "class": "group",
      "id": "4D9C810A-6A6B-4DD1-8B94-E09A35D69415"
    },
    {
      "class": "group",
      "id": "59F11384-2A3C-4072-A076-0FFA47501C91"
    },
    {
      "class": "group",
      "id": "2742AE0D-0A1F-4274-9B02-E991D87F1365"
    },
    {
      "class": "group",
      "id": "702DAA70-6179-452F-BD40-963F5053EF61"
    },
    {
      "class": "group",
      "id": "BAA3C14F-CABC-4E2B-8A50-062465F5B1CE"
    },
    {
      "class": "group",
      "id": "40575807-5FC9-4140-946E-0C4DEF3C3805"
    }
  ],
  "name": "small icon button",
  "nameIsFixed": true,
  "resizingConstraint": 63,
  "resizingType": 0,
  "rotation": 0,
  "shouldBreakMaskChain": false,
  "style": {
    "_class": "style",
    "do_objectID": "8CBE3756-D818-483E-97A0-7C4375E814AF",
    "endDecorationType": 0,
    "miterLimit": 10,
    "startDecorationType": 0
  }
}