{
  "_class": "group",
  "do_objectID": "EDE9B172-3925-4FB2-BA52-0B6A93E84B73",
  "exportOptions": {
    "_class": "exportOptions",
    "do_objectID": "06D829CD-148A-43BC-9CF3-2CEDE70E96FB",
    "exportFormats": [
    ],
    "includedLayerIds": [
    ],
    "layerOptions": 0,
    "shouldTrim": false
  },
  "frame": {
    "_class": "rect",
    "constrainProportions": false,
    "do_objectID": "1F37D8AB-724D-42FE-9549-3D20E046B45A",
    "height": 28,
    "width": 40,
    "x": 212,
    "y": 6
  },
  "hasClickThrough": false,
  "isFlippedHorizontal": false,
  "isFlippedVertical": false,
  "isLocked": false,
  "isVisible": true,
  "layerListExpandedType": 0,
  "layers": [
    {
      "class": "shapeGroup",
      "id": "483A7A4B-D59B-45D7-8DC2-21DB4C554C32"
    },
    {
      "class": "text",
      "id": "AF5B4F0D-3FC9-4016-8B24-AFB7FF97C351"
    }
  ],
  "name": "new 12 tag",
  "nameIsFixed": true,
  "resizingConstraint": 63,
  "resizingType": 0,
  "rotation": 0,
  "shouldBreakMaskChain": false,
  "style": {
    "_class": "style",
    "do_objectID": "7BA28591-D9B2-4B6C-B85A-022E9D632A8E",
    "endDecorationType": 0,
    "miterLimit": 10,
    "startDecorationType": 0
  }
}