{
  "_class": "shapeGroup",
  "clippingMaskMode": 0,
  "do_objectID": "286A3D92-3388-4BF2-9767-56B6C1DA1D59",
  "exportOptions": {
    "_class": "exportOptions",
    "do_objectID": "9091FA1B-4197-4B46-9147-CBEA82CD1A2A",
    "exportFormats": [
    ],
    "includedLayerIds": [
    ],
    "layerOptions": 0,
    "shouldTrim": false
  },
  "frame": {
    "_class": "rect",
    "constrainProportions": false,
    "do_objectID": "1CD5FC04-8826-4429-9BFD-8BEB508C6B97",
    "height": 5.712180518187847,
    "width": 4.94372238373289,
    "x": 48.82588019414035,
    "y": 74.17073606684106
  },
  "hasClickThrough": false,
  "hasClippingMask": false,
  "isFlippedHorizontal": false,
  "isFlippedVertical": false,
  "isLocked": false,
  "isVisible": true,
  "layerListExpandedType": 0,
  "layers": [
    {
      "class": "shapePath",
      "id": "4091CBC9-CED5-46A8-9573-3DC30AE3590C"
    },
    {
      "class": "shapePath",
      "id": "FE9D52BF-14DB-4FB7-8D52-2B62FBE8A652"
    }
  ],
  "name": "Shape",
  "nameIsFixed": false,
  "resizingConstraint": 63,
  "resizingType": 0,
  "rotation": 0,
  "shouldBreakMaskChain": false,
  "style": {
    "_class": "style",
    "blur": {
      "_class": "blur",
      "center": "{0.5, 0.5}",
      "do_objectID": "A220A748-8877-4644-AF1B-5F2352DBB689",
      "isEnabled": false,
      "motionAngle": 0,
      "radius": 28.48966613672496,
      "type": 0
    },
    "do_objectID": "A98AF03F-97A1-4A86-A417-FAE55EAF4453",
    "endDecorationType": 0,
    "fills": [
      {
        "_class": "fill",
        "color": {
          "_class": "color",
          "alpha": 1,
          "blue": 0.8588235294117647,
          "green": 0.8470588235294119,
          "red": 0.7333333333333333
        },
        "fillType": 0,
        "isEnabled": true,
        "noiseIndex": 0,
        "noiseIntensity": 0,
        "patternFillType": 1,
        "patternTileScale": 1
      }
    ],
    "miterLimit": 10,
    "startDecorationType": 0
  },
  "windingRule": 0
}