{
  "_class": "group",
  "do_objectID": "786B9460-DA96-4524-8A49-E6A6C8EAFFB5",
  "exportOptions": {
    "_class": "exportOptions",
    "do_objectID": "63B033CC-BDD8-40BF-B6CA-17CF561B4282",
    "exportFormats": [
    ],
    "includedLayerIds": [
    ],
    "layerOptions": 0,
    "shouldTrim": false
  },
  "frame": {
    "_class": "rect",
    "constrainProportions": false,
    "do_objectID": "BA3125DF-C5CD-48CC-A3FF-037FB726F681",
    "height": 308,
    "width": 350,
    "x": 760,
    "y": 0
  },
  "hasClickThrough": false,
  "isFlippedHorizontal": false,
  "isFlippedVertical": false,
  "isLocked": false,
  "isVisible": true,
  "layerListExpandedType": 0,
  "layers": [
    {
      "class": "text",
      "id": "57A3E836-EF7C-4969-B56C-7440CB73E763"
    },
    {
      "class": "group",
      "id": "FEC49993-FBD6-4214-8A12-A254BC688C82"
    }
  ],
  "name": "03",
  "nameIsFixed": true,
  "resizingConstraint": 57,
  "resizingType": 0,
  "rotation": 0,
  "shouldBreakMaskChain": false,
  "style": {
    "_class": "style",
    "do_objectID": "5808B858-F51B-481B-BE0E-D777209013E7",
    "endDecorationType": 0,
    "miterLimit": 10,
    "startDecorationType": 0
  }
}