{
  "_class": "shapeGroup",
  "clippingMaskMode": 0,
  "do_objectID": "4FECE7F7-B8ED-4F36-852B-00021E3993D3",
  "exportOptions": {
    "_class": "exportOptions",
    "do_objectID": "B6161346-0859-4384-A962-A495B5A7C1A1",
    "exportFormats": [
    ],
    "includedLayerIds": [
    ],
    "layerOptions": 0,
    "shouldTrim": false
  },
  "frame": {
    "_class": "rect",
    "constrainProportions": false,
    "do_objectID": "B9040B46-BF5E-45DF-BA78-49907599F920",
    "height": 5.669749884069,
    "width": 4.554242749731493,
    "x": 23.14232008592912,
    "y": 74.19930047694753
  },
  "hasClickThrough": false,
  "hasClippingMask": false,
  "isFlippedHorizontal": false,
  "isFlippedVertical": false,
  "isLocked": false,
  "isVisible": true,
  "layerListExpandedType": 0,
  "layers": [
    {
      "class": "shapePath",
      "id": "A00B3A9C-F65B-4EAF-ACF6-1C9F3C09A3FC"
    },
    {
      "class": "shapePath",
      "id": "45B5930F-EF5C-4B26-A475-E16506A190CE"
    }
  ],
  "name": "Shape",
  "nameIsFixed": false,
  "resizingConstraint": 63,
  "resizingType": 0,
  "rotation": 0,
  "shouldBreakMaskChain": false,
  "style": {
    "_class": "style",
    "blur": {
      "_class": "blur",
      "center": "{0.5, 0.5}",
      "do_objectID": "23B41384-6ED2-47BD-ABB3-F17E8653637F",
      "isEnabled": false,
      "motionAngle": 0,
      "radius": 28.48966613672496,
      "type": 0
    },
    "do_objectID": "A233E496-B2B7-4AF7-974C-B0666CD5C6E0",
    "endDecorationType": 0,
    "fills": [
      {
        "_class": "fill",
        "color": {
          "_class": "color",
          "alpha": 1,
          "blue": 0.8588235294117647,
          "green": 0.8470588235294119,
          "red": 0.7333333333333333
        },
        "fillType": 0,
        "isEnabled": true,
        "noiseIndex": 0,
        "noiseIntensity": 0,
        "patternFillType": 1,
        "patternTileScale": 1
      }
    ],
    "miterLimit": 10,
    "startDecorationType": 0
  },
  "windingRule": 0
}