{
  "_class": "artboard",
  "backgroundColor": {
    "_class": "color",
    "alpha": 1,
    "blue": 1,
    "do_objectID": "68F87557-5A65-4EAE-87EF-784C18F0703F",
    "green": 1,
    "red": 1
  },
  "do_objectID": "1F1D27BC-5153-4699-9D3D-B8F83CDE7F57",
  "exportOptions": {
    "_class": "exportOptions",
    "do_objectID": "31464919-5BF0-4322-B8AA-08F503EA3778",
    "exportFormats": [
      {
        "_class": "exportFormat",
        "absoluteSize": 0,
        "fileFormat": "png",
        "name": "",
        "namingScheme": 0,
        "scale": 2,
        "visibleScaleType": 0
      }
    ],
    "includedLayerIds": [
    ],
    "layerOptions": 0,
    "shouldTrim": false
  },
  "frame": {
    "_class": "rect",
    "constrainProportions": false,
    "do_objectID": "4B28D80C-F653-4603-92DC-BCEB0B529702",
    "height": 2743,
    "width": 1440,
    "x": 13772,
    "y": -265
  },
  "grid": {
    "_class": "simpleGrid",
    "do_objectID": "FAE348F8-4934-4DEB-97D5-9C004F67C4B3",
    "gridSize": 8,
    "isEnabled": false,
    "thickGridTimes": 8
  },
  "hasBackgroundColor": true,
  "hasClickThrough": false,
  "horizontalRulerData": {
    "_class": "rulerData",
    "base": 0,
    "do_objectID": "97328A67-752F-42A1-8A4A-61034461A870",
    "guides": [
      150,
      1290,
      1195,
      1100,
      1005,
      910,
      815,
      720,
      625,
      530,
      435,
      340,
      245
    ]
  },
  "includeBackgroundColorInExport": true,
  "includeInCloudUpload": true,
  "isFlippedHorizontal": false,
  "isFlippedVertical": false,
  "isFlowHome": false,
  "isLocked": false,
  "isVisible": true,
  "layerListExpandedType": 1,
  "layers": [
    {
      "class": "symbolInstance",
      "id": "931DEDE9-6881-413F-B05D-FAA8FDDC2E17"
    },
    {
      "class": "symbolInstance",
      "id": "1A197D94-7446-41A8-863C-8C8BA19C8CF4"
    },
    {
      "class": "symbolInstance",
      "id": "35A5082A-8445-497B-8E99-9A89A0E1F62F"
    },
    {
      "class": "symbolInstance",
      "id": "11FC2A0C-EA60-4AE6-8561-5264F5FEB66B"
    },
    {
      "class": "symbolInstance",
      "id": "5D6251E8-D615-4A97-9500-9B44560E8A6C"
    }
  ],
  "layout": {
    "_class": "layoutGrid",
    "columnWidth": 65,
    "do_objectID": "1A321644-20E7-4274-8FED-545B1200335A",
    "drawHorizontal": false,
    "drawHorizontalLines": false,
    "drawVertical": true,
    "gutterHeight": 12,
    "gutterWidth": 30,
    "guttersOutside": true,
    "horizontalOffset": 150,
    "isEnabled": false,
    "numberOfColumns": 12,
    "rowHeightMultiplication": 5,
    "totalWidth": 1140
  },
  "name": "Database Desktop #2",
  "nameIsFixed": true,
  "presetDictionary": {
    "allowResizedMatching": 0,
    "height": 1024,
    "name": "Desktop HD",
    "offersLandscapeVariant": 0,
    "width": 1440
  },
  "resizesContent": false,
  "resizingConstraint": 63,
  "resizingType": 0,
  "rotation": 0,
  "shouldBreakMaskChain": true,
  "style": {
    "_class": "style",
    "do_objectID": "DADC053B-2418-4C11-80A2-4E047DBD2959",
    "endDecorationType": 0,
    "miterLimit": 10,
    "startDecorationType": 0
  },
  "userInfo": {
    "com.animaapp.stc-sketch-plugin": {
      "kModelPropertiesKey": {
      }
    }
  },
  "verticalRulerData": {
    "_class": "rulerData",
    "base": 0,
    "do_objectID": "EFA2EB43-488C-43A7-AD19-BEEC1313BDF6",
    "guides": [
    ]
  }
}