{
  "_class": "group",
  "do_objectID": "7DEA036F-77E1-4FE1-B1EF-1B673A7FB81D",
  "exportOptions": {
    "_class": "exportOptions",
    "do_objectID": "D47D2E11-EED6-4092-A212-37184E651DA6",
    "exportFormats": [
    ],
    "includedLayerIds": [
    ],
    "layerOptions": 0,
    "shouldTrim": false
  },
  "frame": {
    "_class": "rect",
    "constrainProportions": false,
    "do_objectID": "A66AE021-57C6-4A16-BA91-52EBE3E2050D",
    "height": 50,
    "width": 118,
    "x": 0,
    "y": 270
  },
  "hasClickThrough": false,
  "isFlippedHorizontal": false,
  "isFlippedVertical": false,
  "isLocked": false,
  "isVisible": true,
  "layerListExpandedType": 0,
  "layers": [
    {
      "class": "shapeGroup",
      "id": "0FBFBF92-0B49-42C1-B453-863F60554A0C"
    },
    {
      "class": "text",
      "id": "576EC14A-BF4D-471A-8092-B4B0D1FA33DC"
    }
  ],
  "name": "disable state button",
  "nameIsFixed": true,
  "resizingConstraint": 63,
  "resizingType": 0,
  "rotation": 0,
  "shouldBreakMaskChain": false,
  "style": {
    "_class": "style",
    "do_objectID": "7FF2C390-78DF-4185-A2D7-1CC91EC14040",
    "endDecorationType": 0,
    "miterLimit": 10,
    "sharedObjectID": "80BAA1CC-6FA8-479C-8BB5-AE860D366ACE",
    "startDecorationType": 0
  }
}