{
  "_class": "shapeGroup",
  "clippingMaskMode": 0,
  "do_objectID": "8E83968B-A68A-45E8-846D-ED7A4E447B9E",
  "exportOptions": {
    "_class": "exportOptions",
    "do_objectID": "930FA4C8-4CC0-4EC4-B27A-1B8102DA6E66",
    "exportFormats": [
    ],
    "includedLayerIds": [
    ],
    "layerOptions": 0,
    "shouldTrim": false
  },
  "frame": {
    "_class": "rect",
    "constrainProportions": false,
    "do_objectID": "8DB63A15-FE34-4389-9709-850C0DA1EE93",
    "height": 5.712180518187847,
    "width": 4.94372238373289,
    "x": 83.52351714365702,
    "y": 74.17073606684106
  },
  "hasClickThrough": false,
  "hasClippingMask": false,
  "isFlippedHorizontal": false,
  "isFlippedVertical": false,
  "isLocked": false,
  "isVisible": true,
  "layerListExpandedType": 0,
  "layers": [
    {
      "class": "shapePath",
      "id": "639B6825-6254-4A68-925D-C2DAA6CB8C03"
    },
    {
      "class": "shapePath",
      "id": "4BCFB2BF-652C-400D-9F65-86A473BB51AA"
    }
  ],
  "name": "Shape",
  "nameIsFixed": false,
  "resizingConstraint": 63,
  "resizingType": 0,
  "rotation": 0,
  "shouldBreakMaskChain": false,
  "style": {
    "_class": "style",
    "blur": {
      "_class": "blur",
      "center": "{0.5, 0.5}",
      "do_objectID": "AEBBEE53-6A40-431F-9B13-1A16CB0AAFD7",
      "isEnabled": false,
      "motionAngle": 0,
      "radius": 28.48966613672496,
      "type": 0
    },
    "do_objectID": "A1633129-F440-4F62-BF17-BE05AF6963A7",
    "endDecorationType": 0,
    "fills": [
      {
        "_class": "fill",
        "color": {
          "_class": "color",
          "alpha": 1,
          "blue": 0.8588235294117647,
          "green": 0.8470588235294119,
          "red": 0.7333333333333333
        },
        "fillType": 0,
        "isEnabled": true,
        "noiseIndex": 0,
        "noiseIntensity": 0,
        "patternFillType": 1,
        "patternTileScale": 1
      }
    ],
    "miterLimit": 10,
    "startDecorationType": 0
  },
  "windingRule": 0
}