{
  "_class": "group",
  "do_objectID": "C0861550-EDD7-4135-857E-7B1C1E33C823",
  "exportOptions": {
    "_class": "exportOptions",
    "do_objectID": "17E1D7B6-7FC6-4E9D-A4B3-E296C8ABE7B6",
    "exportFormats": [
    ],
    "includedLayerIds": [
    ],
    "layerOptions": 0,
    "shouldTrim": false
  },
  "frame": {
    "_class": "rect",
    "constrainProportions": false,
    "do_objectID": "5DC5DBE9-0627-48AB-8025-2EDA3817074C",
    "height": 180,
    "width": 158,
    "x": 346,
    "y": 0
  },
  "hasClickThrough": false,
  "isFlippedHorizontal": false,
  "isFlippedVertical": false,
  "isLocked": false,
  "isVisible": true,
  "layerListExpandedType": 0,
  "layers": [
    {
      "class": "text",
      "id": "79A798B1-0826-4C26-849A-6DE57FC9D801"
    },
    {
      "class": "shapeGroup",
      "id": "7046453F-F96A-4EB5-8688-8303B72DB008"
    }
  ],
  "name": "3",
  "nameIsFixed": true,
  "resizingConstraint": 63,
  "resizingType": 0,
  "rotation": 0,
  "shouldBreakMaskChain": false,
  "style": {
    "_class": "style",
    "do_objectID": "A4D99EDB-DAAB-4692-B4E3-B7ACE396E79F",
    "endDecorationType": 0,
    "miterLimit": 10,
    "startDecorationType": 0
  }
}