{
  "_class": "shapeGroup",
  "clippingMaskMode": 0,
  "do_objectID": "06393431-0BF1-4201-89BD-AB4D5C232F9C",
  "exportOptions": {
    "_class": "exportOptions",
    "do_objectID": "B2809D64-CDC0-4F26-827B-F57BA01ABB31",
    "exportFormats": [
    ],
    "includedLayerIds": [
    ],
    "layerOptions": 0,
    "shouldTrim": false
  },
  "frame": {
    "_class": "rect",
    "constrainProportions": false,
    "do_objectID": "943DCF0F-1EF2-478C-AD22-BF9C61C92515",
    "height": 5.694362193487443,
    "width": 4.309150969237947,
    "x": 20.428976190476,
    "y": 53.08398915786389
  },
  "hasClickThrough": false,
  "hasClippingMask": false,
  "isFlippedHorizontal": false,
  "isFlippedVertical": false,
  "isLocked": false,
  "isVisible": true,
  "layerListExpandedType": 0,
  "layers": [
    {
      "class": "shapePath",
      "id": "E34234A8-196A-4E09-87B8-D07FCB055794"
    }
  ],
  "name": "Shape",
  "nameIsFixed": false,
  "resizingConstraint": 63,
  "resizingType": 0,
  "rotation": 0,
  "shouldBreakMaskChain": false,
  "style": {
    "_class": "style",
    "blur": {
      "_class": "blur",
      "center": "{0.5, 0.5}",
      "do_objectID": "0719BB13-A769-438B-951F-60A251F213B2",
      "isEnabled": false,
      "motionAngle": 0,
      "radius": 22.37578295815953,
      "type": 0
    },
    "do_objectID": "A213BD80-4CB3-43A3-B2FC-6A684CD2C8D5",
    "endDecorationType": 0,
    "fills": [
      {
        "_class": "fill",
        "color": {
          "_class": "color",
          "alpha": 1,
          "blue": 0.8588235294117647,
          "green": 0.8470588235294119,
          "red": 0.7333333333333333
        },
        "fillType": 0,
        "isEnabled": true,
        "noiseIndex": 0,
        "noiseIntensity": 0,
        "patternFillType": 1,
        "patternTileScale": 1
      }
    ],
    "miterLimit": 10,
    "startDecorationType": 0
  },
  "windingRule": 0
}