{
  "_class": "group",
  "do_objectID": "559963FC-5D4C-4323-9BFE-6416920EEB7B",
  "exportOptions": {
    "_class": "exportOptions",
    "do_objectID": "30AC4334-A9DB-40FF-B06F-97A5D8ECC9C1",
    "exportFormats": [
    ],
    "includedLayerIds": [
    ],
    "layerOptions": 0,
    "shouldTrim": false
  },
  "frame": {
    "_class": "rect",
    "constrainProportions": false,
    "do_objectID": "24D65329-9AB7-4D1E-A400-098B713F8310",
    "height": 534,
    "width": 850,
    "x": 830,
    "y": 292
  },
  "hasClickThrough": false,
  "isFlippedHorizontal": false,
  "isFlippedVertical": false,
  "isLocked": false,
  "isVisible": true,
  "layerListExpandedType": 0,
  "layers": [
    {
      "class": "shapeGroup",
      "id": "CA90B5ED-7B1C-408F-AB88-00D7F3F97CCA"
    },
    {
      "class": "group",
      "id": "26B12EE3-522D-4279-9EC8-A6834CED0089"
    },
    {
      "class": "group",
      "id": "A636F664-E0B5-48F6-970B-CEED31CB6599"
    }
  ],
  "name": "MacBook",
  "nameIsFixed": true,
  "resizingConstraint": 47,
  "resizingType": 0,
  "rotation": 0,
  "shouldBreakMaskChain": true,
  "style": {
    "_class": "style",
    "blur": {
      "_class": "blur",
      "center": "{0.5, 0.5}",
      "do_objectID": "6A0650FF-EF01-43DC-B80D-BB839895A5BE",
      "isEnabled": false,
      "motionAngle": 0,
      "radius": 7.700000035762784,
      "type": 0
    },
    "do_objectID": "9DF37726-EE19-4AB6-A025-8313AADB3F8B",
    "endDecorationType": 0,
    "miterLimit": 10,
    "startDecorationType": 0
  }
}