{
  "_class": "group",
  "do_objectID": "0F456D8A-57FA-44DD-8580-96B633B8F77C",
  "exportOptions": {
    "_class": "exportOptions",
    "do_objectID": "8B6F651E-E9BF-4B09-80AF-88FCCAECB6A0",
    "exportFormats": [
    ],
    "includedLayerIds": [
    ],
    "layerOptions": 0,
    "shouldTrim": false
  },
  "frame": {
    "_class": "rect",
    "constrainProportions": false,
    "do_objectID": "9CAC0A14-142D-4F28-AA50-500ACC33B223",
    "height": 180,
    "width": 504,
    "x": 15,
    "y": 112
  },
  "hasClickThrough": false,
  "isFlippedHorizontal": false,
  "isFlippedVertical": false,
  "isLocked": false,
  "isVisible": true,
  "layerListExpandedType": 0,
  "layers": [
    {
      "class": "group",
      "id": "EC11EC23-8D8F-421F-AD5D-58C07402EC2D"
    },
    {
      "class": "group",
      "id": "9B227650-B68B-4E14-920E-DEB9B03EA823"
    },
    {
      "class": "group",
      "id": "74036A48-15D8-43E2-90B7-8083F7DED511"
    }
  ],
  "name": "cards",
  "nameIsFixed": true,
  "resizingConstraint": 63,
  "resizingType": 0,
  "rotation": 0,
  "shouldBreakMaskChain": false,
  "style": {
    "_class": "style",
    "do_objectID": "633288E9-6AA5-4CA7-9A83-0FA1BADE3A85",
    "endDecorationType": 0,
    "miterLimit": 10,
    "startDecorationType": 0
  }
}