{
  "_class": "shapePath",
  "booleanOperation": -1,
  "do_objectID": "C413347A-8647-4C42-B2FE-83FBF233020D",
  "edited": true,
  "exportOptions": {
    "_class": "exportOptions",
    "do_objectID": "ACDE3093-7761-4657-B9B5-A2C28DE919EB",
    "exportFormats": [
    ],
    "includedLayerIds": [
    ],
    "layerOptions": 0,
    "shouldTrim": false
  },
  "frame": {
    "_class": "rect",
    "constrainProportions": false,
    "do_objectID": "CFFF0AA0-CDF6-4331-A3D9-C90CD12C60DB",
    "height": 1.867138166203585,
    "width": 1.869813664596297,
    "x": 0.5235478260869388,
    "y": 0.3009386577802677
  },
  "isClosed": true,
  "isFlippedHorizontal": false,
  "isFlippedVertical": false,
  "isLocked": false,
  "isVisible": true,
  "layerListExpandedType": 0,
  "name": "Path",
  "nameIsFixed": false,
  "pointRadiusBehaviour": 1,
  "points": [
    {
      "_class": "curvePoint",
      "cornerRadius": 0,
      "curveFrom": "{0.61643682714903036, 0.40690570172674967}",
      "curveMode": 4,
      "curveTo": "{0.61000000000000654, 0.45000000000000284}",
      "hasCurveFrom": true,
      "hasCurveTo": false,
      "point": "{0.61000000000000654, 0.45000000000000284}"
    },
    {
      "_class": "curvePoint",
      "cornerRadius": 0,
      "curveFrom": "{0.61000000000000654, 0.14999999999999858}",
      "curveMode": 4,
      "curveTo": "{0.61643682714903036, 0.36309429827326056}",
      "hasCurveFrom": true,
      "hasCurveTo": true,
      "point": "{0.61000000000000654, 0.32000000000000028}"
    },
    {
      "_class": "curvePoint",
      "cornerRadius": 0,
      "curveFrom": "{0.14000000000000057, 0}",
      "curveMode": 2,
      "curveTo": "{0.54000000000000625, 0}",
      "hasCurveFrom": true,
      "hasCurveTo": true,
      "point": "{0.34000000000000341, 0}"
    },
    {
      "_class": "curvePoint",
      "cornerRadius": 0,
      "curveFrom": "{0, 0.45000000000000284}",
      "curveMode": 4,
      "curveTo": "{0.030000000000001137, 0.14999999999999858}",
      "hasCurveFrom": false,
      "hasCurveTo": true,
      "point": "{0, 0.45000000000000284}"
    }
  ],
  "resizingConstraint": 63,
  "resizingType": 0,
  "rotation": 0,
  "shouldBreakMaskChain": false
}