{
  "_class": "shapeGroup",
  "clippingMaskMode": 0,
  "do_objectID": "BD5FE9D7-7C05-48CC-A720-C2D348FCF37D",
  "exportOptions": {
    "_class": "exportOptions",
    "do_objectID": "8DFF5DAF-425B-4474-AADF-566F5D34DF4E",
    "exportFormats": [
    ],
    "includedLayerIds": [
    ],
    "layerOptions": 0,
    "shouldTrim": false
  },
  "frame": {
    "_class": "rect",
    "constrainProportions": false,
    "do_objectID": "FC38780F-D3F6-434B-A86E-5A4A7F74CFC4",
    "height": 2,
    "width": 1140.999999999998,
    "x": 0,
    "y": 51
  },
  "hasClickThrough": true,
  "hasClippingMask": false,
  "isFlippedHorizontal": false,
  "isFlippedVertical": false,
  "isLocked": false,
  "isVisible": true,
  "layerListExpandedType": 0,
  "layers": [
    {
      "class": "rectangle",
      "id": "70BEA44C-8528-49C5-809E-BEF2EC48D6E7"
    }
  ],
  "name": "line",
  "nameIsFixed": true,
  "resizingConstraint": 63,
  "resizingType": 0,
  "rotation": 0,
  "shouldBreakMaskChain": false,
  "style": {
    "_class": "style",
    "do_objectID": "22BC2FD9-DA02-408D-B657-959ABE6834D3",
    "endDecorationType": 0,
    "fills": [
      {
        "_class": "fill",
        "color": {
          "_class": "color",
          "alpha": 1,
          "blue": 0.96,
          "green": 0.96,
          "red": 0.96
        },
        "fillType": 0,
        "isEnabled": true,
        "noiseIndex": 0,
        "noiseIntensity": 0,
        "patternFillType": 0,
        "patternTileScale": 1
      }
    ],
    "miterLimit": 10,
    "startDecorationType": 0
  },
  "windingRule": 1
}