{
  "_class": "text",
  "attributedString": {
    "_class": "attributedString",
    "attributes": [
      {
        "_class": "stringAttribute",
        "attributes": {
          "MSAttributedStringColorAttribute": {
            "_class": "color",
            "alpha": 1,
            "blue": 0.5098039215686274,
            "green": 0.4745098039215684,
            "red": 0.06666666666666665
          },
          "MSAttributedStringFontAttribute": {
            "_class": "fontDescriptor",
            "attributes": {
              "name": "OpenSans-Regular",
              "size": 14
            }
          },
          "kerning": 0.2000000029802322,
          "paragraphStyle": {
            "_class": "paragraphStyle",
            "alignment": 0,
            "baseWritingDirection": 0,
            "maximumLineHeight": 22,
            "minimumLineHeight": 22
          }
        },
        "length": 455,
        "location": 0
      }
    ],
    "string": "Beispielsweise kennen viele Patienten die Bedeutung bestimmte Fachausdrücke, wie “Wechselwirkungen”, “Hilfsstoffe” oder “Pharmakokinetik” nicht und können auch mit den Angaben zu Nebenwirkungen nicht immer direkt etwas anfangen. Bereits die EU kritisierte die Komplexität der Beipackzettel und fordert Hersteller dazu auf, diese benutzerfreundlicher zu gestalten. Ein nicht zu unterschätzendes Problem ist auch die Schriftgröße gerade für ältere Menschen."
  },
  "automaticallyDrawOnUnderlyingPath": false,
  "do_objectID": "2AE67B9A-5B4E-4458-B0DA-9ACB2DD6C3F4",
  "dontSynchroniseWithSymbol": false,
  "exportOptions": {
    "_class": "exportOptions",
    "do_objectID": "1078E559-F88D-4B9F-BB6C-0E41493F0EBA",
    "exportFormats": [
    ],
    "includedLayerIds": [
    ],
    "layerOptions": 0,
    "shouldTrim": false
  },
  "frame": {
    "_class": "rect",
    "constrainProportions": false,
    "do_objectID": "AF3B169D-CC73-45DC-A9BC-D384E66604C9",
    "height": 264,
    "width": 294,
    "x": 56,
    "y": 0
  },
  "glyphBounds": "{{0, 5}, {290, 254}}",
  "isFlippedHorizontal": false,
  "isFlippedVertical": false,
  "isLocked": false,
  "isVisible": true,
  "layerListExpandedType": 0,
  "lineSpacingBehaviour": 2,
  "name": "Beispielsweise kenne",
  "nameIsFixed": false,
  "resizingConstraint": 57,
  "resizingType": 0,
  "rotation": 0,
  "shouldBreakMaskChain": false,
  "style": {
    "_class": "style",
    "do_objectID": "EBD36097-1987-4ECA-A2AB-64BC8FA71345",
    "endDecorationType": 0,
    "miterLimit": 10,
    "sharedObjectID": "EF1B112A-0D98-4BB5-94B2-DA92E2995040",
    "startDecorationType": 0,
    "textStyle": {
      "_class": "textStyle",
      "encodedAttributes": {
        "MSAttributedStringColorAttribute": {
          "_class": "color",
          "alpha": 1,
          "blue": 0.5098039215686274,
          "green": 0.4745098039215684,
          "red": 0.06666666666666665
        },
        "MSAttributedStringFontAttribute": {
          "_class": "fontDescriptor",
          "attributes": {
            "name": "OpenSans-Regular",
            "size": 14
          }
        },
        "kerning": 0.2000000029802322,
        "paragraphStyle": {
          "_class": "paragraphStyle",
          "alignment": 0,
          "baseWritingDirection": 0,
          "maximumLineHeight": 22,
          "minimumLineHeight": 22
        }
      },
      "verticalAlignment": 0
    }
  },
  "textBehaviour": 1
}