{
  "_class": "shapeGroup",
  "clippingMaskMode": 0,
  "do_objectID": "5AE69AED-27EE-4918-9C9E-0E8EC4EF2131",
  "exportOptions": {
    "_class": "exportOptions",
    "do_objectID": "76969335-9BA8-44B5-8909-FB4B82D60341",
    "exportFormats": [
    ],
    "includedLayerIds": [
    ],
    "layerOptions": 0,
    "shouldTrim": false
  },
  "frame": {
    "_class": "rect",
    "constrainProportions": false,
    "do_objectID": "7097E226-DB1C-4E89-B6A8-E07DBA9966AF",
    "height": 3.538549986467224,
    "width": 1.930998925886158,
    "x": 35.28696025778729,
    "y": 47.28696352704628
  },
  "hasClickThrough": false,
  "hasClippingMask": false,
  "isFlippedHorizontal": false,
  "isFlippedVertical": false,
  "isLocked": false,
  "isVisible": true,
  "layerListExpandedType": 0,
  "layers": [
    {
      "class": "shapePath",
      "id": "967F0797-0156-4E4C-8027-20397E4F589F"
    }
  ],
  "name": "Shape",
  "nameIsFixed": false,
  "resizingConstraint": 63,
  "resizingType": 0,
  "rotation": 0,
  "shouldBreakMaskChain": false,
  "style": {
    "_class": "style",
    "blur": {
      "_class": "blur",
      "center": "{0.5, 0.5}",
      "do_objectID": "A4AF9ED6-E54E-4E31-9F6B-EF989CDE6B43",
      "isEnabled": false,
      "motionAngle": 0,
      "radius": 18.23338415391501,
      "type": 0
    },
    "do_objectID": "773DC8B3-8EEB-40F9-929F-3EC2E322CA77",
    "endDecorationType": 0,
    "fills": [
      {
        "_class": "fill",
        "color": {
          "_class": "color",
          "alpha": 1,
          "blue": 0.8588235294117647,
          "green": 0.8470588235294119,
          "red": 0.7333333333333333
        },
        "fillType": 0,
        "isEnabled": true,
        "noiseIndex": 0,
        "noiseIntensity": 0,
        "patternFillType": 1,
        "patternTileScale": 1
      }
    ],
    "miterLimit": 10,
    "startDecorationType": 0
  },
  "windingRule": 0
}