{
  "_class": "shapeGroup",
  "clippingMaskMode": 0,
  "do_objectID": "C3A0FF64-505B-4185-B445-0D17A7647519",
  "exportOptions": {
    "_class": "exportOptions",
    "do_objectID": "BD8B4724-06C9-45C4-A0A6-949C01D1E903",
    "exportFormats": [
    ],
    "includedLayerIds": [
    ],
    "layerOptions": 0,
    "shouldTrim": false
  },
  "frame": {
    "_class": "rect",
    "constrainProportions": false,
    "do_objectID": "AE5BBE93-7D1F-4BFF-B012-97F8CC9B75EA",
    "height": 312,
    "width": 498,
    "x": 79,
    "y": 26
  },
  "hasClickThrough": false,
  "hasClippingMask": false,
  "isFlippedHorizontal": false,
  "isFlippedVertical": false,
  "isLocked": false,
  "isVisible": true,
  "layerListExpandedType": 1,
  "layers": [
    {
      "class": "rectangle",
      "id": "2B5881B1-53B9-440E-B74C-C617BB516472"
    }
  ],
  "name": "Screen",
  "nameIsFixed": true,
  "resizingConstraint": 63,
  "resizingType": 0,
  "rotation": 0,
  "shouldBreakMaskChain": false,
  "style": {
    "_class": "style",
    "do_objectID": "8EE5E5B7-D304-421B-B7E2-DED6B20C6280",
    "endDecorationType": 0,
    "fills": [
      {
        "_class": "fill",
        "color": {
          "_class": "color",
          "alpha": 1,
          "blue": 0.9764705882352941,
          "green": 0.9725490196078431,
          "red": 0.9529411764705882
        },
        "fillType": 0,
        "isEnabled": true,
        "noiseIndex": 0,
        "noiseIntensity": 0,
        "patternFillType": 1,
        "patternTileScale": 1
      }
    ],
    "miterLimit": 10,
    "startDecorationType": 0
  },
  "windingRule": 1
}