{
  "_class": "bitmap",
  "clippingMask": "{{0, 0}, {1, 1}}",
  "do_objectID": "EACB9EC2-7D76-421A-B2C4-A08E2218A004",
  "exportOptions": {
    "_class": "exportOptions",
    "do_objectID": "550896E9-D6EC-459E-950C-3E3F61702C53",
    "exportFormats": [
    ],
    "includedLayerIds": [
    ],
    "layerOptions": 0,
    "shouldTrim": false
  },
  "fillReplacesImage": false,
  "frame": {
    "_class": "rect",
    "constrainProportions": true,
    "do_objectID": "298BDA53-DA3C-4150-982B-2E25671A1ADB",
    "height": 22,
    "width": 222.6007954370279,
    "x": 109,
    "y": 39
  },
  "image": {
    "_class": "MSJSONFileReference",
    "_ref": "images/7796896a6eebe588a2ec7d07004682a0c996909d.png",
    "_ref_class": "MSImageData"
  },
  "intendedDPI": 0,
  "isFlippedHorizontal": false,
  "isFlippedVertical": false,
  "isLocked": false,
  "isVisible": true,
  "layerListExpandedType": 0,
  "name": "Logo_4c_RGB",
  "nameIsFixed": false,
  "resizingConstraint": 63,
  "resizingType": 0,
  "rotation": 0,
  "shouldBreakMaskChain": false,
  "style": {
    "_class": "style",
    "blur": {
      "_class": "blur",
      "center": "{0.5, 0.5}",
      "do_objectID": "89F5AE5D-5CF9-413D-9BD3-96151CF54F77",
      "isEnabled": false,
      "motionAngle": 0,
      "radius": 1.320000081062318,
      "type": 0
    },
    "do_objectID": "71613E6A-586D-4858-916D-3CFAB65A43D5",
    "endDecorationType": 0,
    "miterLimit": 10,
    "startDecorationType": 0
  }
}