{
  "_class": "shapeGroup",
  "clippingMaskMode": 0,
  "do_objectID": "C36C566B-741D-422F-B318-24D8DF3D6E97",
  "exportOptions": {
    "_class": "exportOptions",
    "do_objectID": "A20EE0ED-C45C-4F92-9D87-4D2F0E186AEB",
    "exportFormats": [
    ],
    "includedLayerIds": [
    ],
    "layerOptions": 0,
    "shouldTrim": false
  },
  "frame": {
    "_class": "rect",
    "constrainProportions": false,
    "do_objectID": "2ABF017C-D25F-4BCB-9FF6-4F1159D9523C",
    "height": 9.12156097560975,
    "width": 6.551535980148877,
    "x": 55.59825806451614,
    "y": 4.609951219512196
  },
  "hasClickThrough": false,
  "hasClippingMask": false,
  "isFlippedHorizontal": false,
  "isFlippedVertical": false,
  "isLocked": false,
  "isVisible": true,
  "layerListExpandedType": 0,
  "layers": [
    {
      "class": "shapePath",
      "id": "47686695-C668-4970-9274-5AC554657161"
    }
  ],
  "name": "Fill 6",
  "nameIsFixed": false,
  "resizingConstraint": 63,
  "resizingType": 0,
  "rotation": 0,
  "shouldBreakMaskChain": false,
  "style": {
    "_class": "style",
    "blur": {
      "_class": "blur",
      "center": "{0.5, 0.5}",
      "do_objectID": "825141CC-22ED-457B-B483-2BD7C58A5F64",
      "isEnabled": false,
      "motionAngle": 0,
      "radius": 3.902439024390244,
      "type": 0
    },
    "do_objectID": "25A9CF43-7E51-4CD0-B5D5-4D9CBCB2E4ED",
    "endDecorationType": 0,
    "fills": [
      {
        "_class": "fill",
        "color": {
          "_class": "color",
          "alpha": 1,
          "blue": 1,
          "green": 1,
          "red": 1
        },
        "fillType": 0,
        "isEnabled": true,
        "noiseIndex": 0,
        "noiseIntensity": 0,
        "patternFillType": 1,
        "patternTileScale": 1
      }
    ],
    "miterLimit": 10,
    "startDecorationType": 0
  },
  "windingRule": 1
}