{
  "_class": "shapeGroup",
  "clippingMaskMode": 0,
  "do_objectID": "91FD4360-E9E4-429B-A120-B16028A54620",
  "exportOptions": {
    "_class": "exportOptions",
    "do_objectID": "5AC59455-1764-47B1-A300-D289674ABF24",
    "exportFormats": [
    ],
    "includedLayerIds": [
    ],
    "layerOptions": 0,
    "shouldTrim": false
  },
  "frame": {
    "_class": "rect",
    "constrainProportions": false,
    "do_objectID": "C350ABC1-88F5-4DDB-8BE2-25C900F4C907",
    "height": 21.21288634050133,
    "width": 13.44932944606403,
    "x": 49.53655976676378,
    "y": 4.363021432793144
  },
  "hasClickThrough": false,
  "hasClippingMask": false,
  "isFlippedHorizontal": false,
  "isFlippedVertical": false,
  "isLocked": false,
  "isVisible": true,
  "layerListExpandedType": 0,
  "layers": [
    {
      "class": "shapePath",
      "id": "203D22C3-60DB-45AB-9804-D829C3BADAA0"
    }
  ],
  "name": "Shape",
  "nameIsFixed": false,
  "resizingConstraint": 63,
  "resizingType": 0,
  "rotation": 0,
  "shouldBreakMaskChain": false,
  "style": {
    "_class": "style",
    "blur": {
      "_class": "blur",
      "center": "{0.5, 0.5}",
      "do_objectID": "B19E442E-B966-435F-BB96-908E7A23CAD3",
      "isEnabled": false,
      "motionAngle": 0,
      "radius": 16.53160163288294,
      "type": 0
    },
    "do_objectID": "B759B58F-AC1B-409F-9F32-918E615E4318",
    "endDecorationType": 0,
    "fills": [
      {
        "_class": "fill",
        "color": {
          "_class": "color",
          "alpha": 1,
          "blue": 0.8588235294117647,
          "green": 0.8470588235294119,
          "red": 0.7333333333333333
        },
        "fillType": 0,
        "isEnabled": true,
        "noiseIndex": 0,
        "noiseIntensity": 0,
        "patternFillType": 1,
        "patternTileScale": 1
      }
    ],
    "miterLimit": 10,
    "startDecorationType": 0
  },
  "windingRule": 0
}