{
  "_class": "shapeGroup",
  "clippingMaskMode": 0,
  "do_objectID": "8C41086C-AC0F-42B1-B834-89CF4A300107",
  "exportOptions": {
    "_class": "exportOptions",
    "do_objectID": "084E2CD1-E3CE-4EDB-844A-DB66B8FDA59C",
    "exportFormats": [
    ],
    "includedLayerIds": [
    ],
    "layerOptions": 0,
    "shouldTrim": false
  },
  "frame": {
    "_class": "rect",
    "constrainProportions": false,
    "do_objectID": "83F51A72-7F51-4160-A2FC-46F37D3D5EDC",
    "height": 2.843653579423226,
    "width": 1.869813664596274,
    "x": 5.777724223602493,
    "y": 61.78327333351496
  },
  "hasClickThrough": false,
  "hasClippingMask": false,
  "isFlippedHorizontal": false,
  "isFlippedVertical": false,
  "isLocked": false,
  "isVisible": true,
  "layerListExpandedType": 0,
  "layers": [
    {
      "class": "shapePath",
      "id": "FDAD2A7C-26D9-473A-88E9-2D8A1742C4BE"
    }
  ],
  "name": "Shape",
  "nameIsFixed": false,
  "resizingConstraint": 63,
  "resizingType": 0,
  "rotation": 0,
  "shouldBreakMaskChain": false,
  "style": {
    "_class": "style",
    "blur": {
      "_class": "blur",
      "center": "{0.5, 0.5}",
      "do_objectID": "B5E97D83-9C99-4B2F-8BB3-78326F5302EC",
      "isEnabled": false,
      "motionAngle": 0,
      "radius": 18.82980326175335,
      "type": 0
    },
    "do_objectID": "1E56FF6C-C881-4587-AF2D-E96CE2CB9482",
    "endDecorationType": 0,
    "fills": [
      {
        "_class": "fill",
        "color": {
          "_class": "color",
          "alpha": 1,
          "blue": 0.7803921568627451,
          "green": 0.7647058823529412,
          "red": 0.5843137254901961
        },
        "fillType": 0,
        "isEnabled": true,
        "noiseIndex": 0,
        "noiseIntensity": 0,
        "patternFillType": 1,
        "patternTileScale": 1
      }
    ],
    "miterLimit": 10,
    "startDecorationType": 0
  },
  "windingRule": 0
}