{
  "_class": "text",
  "attributedString": {
    "_class": "attributedString",
    "attributes": [
      {
        "_class": "stringAttribute",
        "attributes": {
          "MSAttributedStringColorAttribute": {
            "_class": "color",
            "alpha": 1,
            "blue": 0.5098039215686274,
            "green": 0.4745098039215684,
            "red": 0.06666666666666665
          },
          "MSAttributedStringFontAttribute": {
            "_class": "fontDescriptor",
            "attributes": {
              "name": "OpenSans-Regular",
              "size": 10
            }
          },
          "paragraphStyle": {
            "_class": "paragraphStyle",
            "alignment": 2,
            "baseWritingDirection": 0,
            "maximumLineHeight": 16,
            "minimumLineHeight": 16
          }
        },
        "length": 56,
        "location": 0
      }
    ],
    "string": "Antibiotika - die Wunderwaffe gegen Bakterieninfektionen"
  },
  "automaticallyDrawOnUnderlyingPath": false,
  "do_objectID": "AB2F522E-D8B9-4518-B074-C90DE40505B7",
  "dontSynchroniseWithSymbol": false,
  "exportOptions": {
    "_class": "exportOptions",
    "do_objectID": "2A35F4AB-DFE4-4DEC-BF19-3ACF6487AD29",
    "exportFormats": [
    ],
    "includedLayerIds": [
    ],
    "layerOptions": 0,
    "shouldTrim": false
  },
  "frame": {
    "_class": "rect",
    "constrainProportions": false,
    "do_objectID": "E036F8BC-D388-487D-BEF2-95F1BB0FAB15",
    "height": 32,
    "width": 158,
    "x": 0,
    "y": 132
  },
  "glyphBounds": "{{9, 4}, {139, 27}}",
  "isFlippedHorizontal": false,
  "isFlippedVertical": false,
  "isLocked": false,
  "isVisible": true,
  "layerListExpandedType": 0,
  "lineSpacingBehaviour": 2,
  "name": "Antibiotika - die Wu",
  "nameIsFixed": false,
  "resizingConstraint": 63,
  "resizingType": 0,
  "rotation": 0,
  "shouldBreakMaskChain": false,
  "style": {
    "_class": "style",
    "do_objectID": "C9C6F26E-50B3-42F7-8FF8-A514073255E5",
    "endDecorationType": 0,
    "miterLimit": 10,
    "sharedObjectID": "F8F90D89-2228-4B7B-B8D4-52EA37B9529B",
    "startDecorationType": 0,
    "textStyle": {
      "_class": "textStyle",
      "do_objectID": "BDDA6A5D-A753-45FD-90D3-F52E88C068AE",
      "encodedAttributes": {
        "MSAttributedStringColorAttribute": {
          "_class": "color",
          "alpha": 1,
          "blue": 0.5098039215686274,
          "green": 0.4745098039215684,
          "red": 0.06666666666666665
        },
        "MSAttributedStringFontAttribute": {
          "_class": "fontDescriptor",
          "attributes": {
            "name": "OpenSans-Regular",
            "size": 10
          }
        },
        "paragraphStyle": {
          "_class": "paragraphStyle",
          "alignment": 2,
          "baseWritingDirection": 0,
          "maximumLineHeight": 16,
          "minimumLineHeight": 16
        }
      },
      "verticalAlignment": 0
    }
  },
  "textBehaviour": 1
}