{
  "_class": "artboard",
  "backgroundColor": {
    "_class": "color",
    "alpha": 1,
    "blue": 1,
    "do_objectID": "CDFB5E34-6990-4D30-A307-21D055A42CE2",
    "green": 1,
    "red": 1
  },
  "do_objectID": "511CF964-0835-4FCB-A69A-A0B17FAD5C1B",
  "exportOptions": {
    "_class": "exportOptions",
    "do_objectID": "8B8E43DD-B1E4-4142-8D83-669EA7363E4C",
    "exportFormats": [
      {
        "_class": "exportFormat",
        "absoluteSize": 0,
        "fileFormat": "png",
        "name": "",
        "namingScheme": 0,
        "scale": 2,
        "visibleScaleType": 0
      }
    ],
    "includedLayerIds": [
    ],
    "layerOptions": 0,
    "shouldTrim": false
  },
  "frame": {
    "_class": "rect",
    "constrainProportions": false,
    "do_objectID": "B52524E9-A224-43AC-82D4-5D5A9B9E3FC2",
    "height": 5863,
    "width": 1440,
    "x": -333,
    "y": 4630
  },
  "grid": {
    "_class": "simpleGrid",
    "do_objectID": "B54CD8D3-B426-4144-96FE-DF0A0244F618",
    "gridSize": 8,
    "isEnabled": false,
    "thickGridTimes": 8
  },
  "hasBackgroundColor": true,
  "hasClickThrough": true,
  "horizontalRulerData": {
    "_class": "rulerData",
    "base": 0,
    "do_objectID": "15C8C58E-A63F-4C34-BDDA-08E266313DE7",
    "guides": [
      150,
      1290,
      1195,
      1100,
      1005,
      910,
      815,
      720,
      625,
      530,
      435,
      340,
      245
    ]
  },
  "includeBackgroundColorInExport": true,
  "includeInCloudUpload": true,
  "isFlippedHorizontal": false,
  "isFlippedVertical": false,
  "isFlowHome": false,
  "isLocked": false,
  "isVisible": true,
  "layerListExpandedType": 2,
  "layers": [
    {
      "class": "group",
      "id": "41DBCA61-EB55-4C29-8B5C-6F6493763666"
    },
    {
      "class": "group",
      "id": "472F3D75-AB38-40BE-ADDE-B4BD5D4F5132"
    },
    {
      "class": "group",
      "id": "80D40AF5-A963-4DC4-AE2F-6159F15F99CC"
    },
    {
      "class": "group",
      "id": "6654B8F8-D49A-4246-ADEF-A8D736F6D0B8"
    },
    {
      "class": "group",
      "id": "5F6231DD-4C3A-4896-89CF-2EA2DE3ED034"
    },
    {
      "class": "group",
      "id": "261EA199-AB6A-4DD5-BDF1-73FCDE92C1B5"
    },
    {
      "class": "group",
      "id": "D867787D-A227-40CA-9797-9587640AC353"
    },
    {
      "class": "group",
      "id": "A708031F-CD0E-4167-A3B3-EAAAD6AAA92C"
    }
  ],
  "layout": {
    "_class": "layoutGrid",
    "columnWidth": 65,
    "do_objectID": "E84395F1-B7E2-47C3-B663-A2C13A1CF1BE",
    "drawHorizontal": false,
    "drawHorizontalLines": false,
    "drawVertical": true,
    "gutterHeight": 12,
    "gutterWidth": 30,
    "guttersOutside": true,
    "horizontalOffset": 150,
    "isEnabled": false,
    "numberOfColumns": 12,
    "rowHeightMultiplication": 5,
    "totalWidth": 1140
  },
  "name": "Home",
  "nameIsFixed": true,
  "presetDictionary": {
    "allowResizedMatching": 0,
    "height": 1024,
    "name": "Desktop HD",
    "offersLandscapeVariant": 0,
    "width": 1440
  },
  "resizesContent": false,
  "resizingConstraint": 63,
  "resizingType": 0,
  "rotation": 0,
  "shouldBreakMaskChain": true,
  "style": {
    "_class": "style",
    "do_objectID": "D3E74227-2DB4-4E91-B759-35E908C146BB",
    "endDecorationType": 0,
    "miterLimit": 10,
    "startDecorationType": 0
  },
  "userInfo": {
    "com.animaapp.stc-sketch-plugin": {
      "kModelPropertiesKey": {
      }
    }
  },
  "verticalRulerData": {
    "_class": "rulerData",
    "base": 0,
    "do_objectID": "D4D93146-F934-4215-BE71-85D6049AFBEE",
    "guides": [
      1024
    ]
  }
}