{
  "_class": "shapePath",
  "booleanOperation": 0,
  "do_objectID": "234166F8-8ADA-4091-80B9-B26DFBD80FC8",
  "edited": true,
  "exportOptions": {
    "_class": "exportOptions",
    "do_objectID": "CB2DBFE2-F908-449C-B85A-8323618949CA",
    "exportFormats": [
    ],
    "includedLayerIds": [
    ],
    "layerOptions": 0,
    "shouldTrim": false
  },
  "frame": {
    "_class": "rect",
    "constrainProportions": false,
    "do_objectID": "287A75B4-C5B6-4641-8FD7-EB577165547A",
    "height": 439.0000000000003,
    "width": 1440.004410996522,
    "x": 0,
    "y": 0
  },
  "isClosed": true,
  "isFlippedHorizontal": false,
  "isFlippedVertical": false,
  "isLocked": false,
  "isVisible": true,
  "layerListExpandedType": 0,
  "name": "Path",
  "nameIsFixed": false,
  "pointRadiusBehaviour": 1,
  "points": [
    {
      "_class": "curvePoint",
      "cornerRadius": 0,
      "curveFrom": "{0.99999691901683818, 0.15315295446788837}",
      "curveMode": 1,
      "curveTo": "{0.99999693681735335, 0}",
      "hasCurveFrom": false,
      "hasCurveTo": false,
      "point": "{0.99999693681735335, 0}"
    },
    {
      "_class": "curvePoint",
      "cornerRadius": 0,
      "curveFrom": "{1.0000013112797985, 1.0040855449718125}",
      "curveMode": 1,
      "curveTo": "{0.99999693681735391, 0.76551724137930932}",
      "hasCurveFrom": false,
      "hasCurveTo": false,
      "point": "{0.99999693681735391, 0.99999999999999845}"
    },
    {
      "_class": "curvePoint",
      "cornerRadius": 0,
      "curveFrom": "{0, 1}",
      "curveMode": 1,
      "curveTo": "{0.066666462454490261, 0.944827586206895}",
      "hasCurveFrom": false,
      "hasCurveTo": false,
      "point": "{0, 1}"
    },
    {
      "_class": "curvePoint",
      "cornerRadius": 0,
      "curveFrom": "{0, 0}",
      "curveMode": 1,
      "curveTo": "{0, 0}",
      "hasCurveFrom": false,
      "hasCurveTo": false,
      "point": "{0, 0}"
    }
  ],
  "resizingConstraint": 63,
  "resizingType": 0,
  "rotation": 0,
  "shouldBreakMaskChain": false
}